uw_msca/VERSION
uw_msca/__init__.py
uw_msca/access_rights.py
uw_msca/dao.py
uw_msca/delegate.py
uw_msca/models.py
uw_msca/shared_drive.py
uw_msca/test.py
uw_msca/util.py
uw_msca/validate_user.py
uw_msca/resources/msca/file/google/report_response_fixture
uw_msca/resources/msca/file/google/token_response_fixture
uw_msca/resources/msca/file/google/v1/drive/defaultou
uw_msca/resources/msca/file/google/v1/drive/getfile
uw_msca/resources/msca/file/google/v1/drive/0AIdwn8Py42DEADBEEF/setquota
uw_msca/resources/msca/file/prtmbx/v1/getaccesstypes
uw_msca/resources/msca/file/prtmbx/v1/getdelegatecsv
uw_msca/resources/msca/file/prtmbx/v1/getdelegates_netid_bill
uw_msca/resources/msca/file/prtmbx/v1/getdelegates_netid_javerage
uw_msca/resources/msca/file/prtmbx/v1/removedelegateperms
uw_msca/resources/msca/file/prtmbx/v1/setdelegateperms
uw_msca/resources/msca/file/prtmbx/v1/validateuser_name_jstaff
uw_msca/resources/msca/file/prtmbx/v1/bill/getdelegates
uw_msca/resources/msca/file/prtmbx/v1/javerage/getdelegates
uw_msca/resources/msca/file/prtmbx/v1/jstaff/removedelegateperms/javerage/FullAccess
uw_msca/resources/msca/file/prtmbx/v1/jstaff/removedelegateperms/javerage/FullAccessandSendAs
uw_msca/resources/msca/file/prtmbx/v1/jstaff/removedelegateperms/javerage/SendAs
uw_msca/resources/msca/file/prtmbx/v1/jstaff/removedelegateperms/javerage/SendOnBehalf
uw_msca/resources/msca/file/prtmbx/v1/jstaff/setdelegateperms/javerage/FullAccess
uw_msca/resources/msca/file/prtmbx/v1/jstaff/setdelegateperms/javerage/FullAccessandSendAs
uw_msca/resources/msca/file/prtmbx/v1/jstaff/setdelegateperms/javerage/SendAs
uw_msca/resources/msca/file/prtmbx/v1/jstaff/setdelegateperms/javerage/SendOnBehalf
uw_msca/resources/msca/file/prtmbx/v1/validateuser/bill
uw_msca/resources/msca/file/prtmbx/v1/validateuser/bill.http-headers
uw_msca/resources/msca/file/prtmbx/v1/validateuser/javerage
uw_msca/tests/__init__.py
uw_msca/tests/test_access_rights.py
uw_msca/tests/test_delegates.py
uw_restclients_msca-0.2.1.dist-info/licenses/LICENSE
uw_restclients_msca-0.2.1.dist-info/METADATA
uw_restclients_msca-0.2.1.dist-info/WHEEL
uw_restclients_msca-0.2.1.dist-info/top_level.txt
uw_restclients_msca-0.2.1.dist-info/RECORD
