Metadata-Version: 2.4
Name: UW-RestClients-MSCA
Version: 0.2.1
Summary: A library for connecting to the UW NetID API
Home-page: https://github.com/uw-it-aca/uw-restclients-msca
Author: UW-IT AXDD
Author-email: aca-it@uw.edu
License: Apache License, Version 2.0
Classifier: Intended Audience :: Developers
Classifier: License :: OSI Approved :: Apache Software License
Classifier: Operating System :: OS Independent
Classifier: Programming Language :: Python
Classifier: Programming Language :: Python :: 3.6
License-File: LICENSE
Requires-Dist: UW-RestClients-Core~=1.3
Dynamic: author
Dynamic: author-email
Dynamic: classifier
Dynamic: description
Dynamic: home-page
Dynamic: license
Dynamic: license-file
Dynamic: requires-dist
Dynamic: summary
